setup.py
dsnd_probability_sos_o3/Binomialdistribution.py
dsnd_probability_sos_o3/Gaussiandistribution.py
dsnd_probability_sos_o3/Generaldistribution.py
dsnd_probability_sos_o3/__init__.py
dsnd_probability_sos_o3.egg-info/PKG-INFO
dsnd_probability_sos_o3.egg-info/SOURCES.txt
dsnd_probability_sos_o3.egg-info/dependency_links.txt
dsnd_probability_sos_o3.egg-info/not-zip-safe
dsnd_probability_sos_o3.egg-info/top_level.txt